{"url":"http:\/\/192.168.100.5:8080\/laporan\/setoranexcel","method":"POST","isAJAX":false,"startTime":1667480932.732567,"totalTime":213.79999999999998,"totalMemory":"11.527","segmentDuration":35,"segmentCount":7,"CI_VERSION":"4.2.3","collectors":[{"title":"Timers","titleSafe":"timers","titleDetails":"","display":[],"badgeValue":null,"isEmpty":false,"hasTabContent":false,"hasLabel":false,"icon":"","hasTimelineData":true,"timelineData":[{"name":"Bootstrap","component":"Timer","start":1667480932.760768,"duration":0.032462120056152344},{"name":"Routing","component":"Timer","start":1667480932.793232,"duration":0.0022411346435546875},{"name":"Before Filters","component":"Timer","start":1667480932.802603,"duration":0.008231878280639648},{"name":"Controller","component":"Timer","start":1667480932.810839,"duration":0.13547301292419434},{"name":"Controller Constructor","component":"Timer","start":1667480932.810841,"duration":0.017184019088745117},{"name":"After Filters","component":"Timer","start":1667480932.946336,"duration":0.0008699893951416016}]},{"title":"Database","titleSafe":"database","titleDetails":"(7 total Queries, 7 of them unique across 1 Connection)","display":{"queries":[{"hover":"","class":"","duration":"0.55 ms","sql":"<strong>SELECT<\/strong> *\n<strong>FROM<\/strong> `setoran`\n<strong>WHERE<\/strong> `tanggal` BETWEEN &quot;2022-10-01&quot; and &quot;2022-10-31&quot;","trace":[{"file":"SYSTEMPATH\\Database\\BaseBuilder.php:1585","function":"\u00a0\u00a0\u00a0\u00a0\u00a0\u00a0\u00a0\u00a0CodeIgniter\\Database\\BaseConnection->query()","index":"\u00a0\u00a01\u00a0\u00a0\u00a0\u00a0"},{"file":"SYSTEMPATH\\Model.php:222","function":"\u00a0\u00a0\u00a0\u00a0\u00a0\u00a0\u00a0\u00a0CodeIgniter\\Database\\BaseBuilder->get()","index":"\u00a0\u00a02\u00a0\u00a0\u00a0\u00a0"},{"file":"SYSTEMPATH\\BaseModel.php:584","function":"\u00a0\u00a0\u00a0\u00a0\u00a0\u00a0\u00a0\u00a0CodeIgniter\\Model->doFindAll()","index":"\u00a0\u00a03\u00a0\u00a0\u00a0\u00a0"},{"file":"APPPATH\\Controllers\\Laporan.php:84","function":"\u00a0\u00a0\u00a0\u00a0\u00a0\u00a0\u00a0\u00a0CodeIgniter\\BaseModel->findAll()","index":"\u00a0\u00a04\u00a0\u00a0\u00a0\u00a0"},{"file":"SYSTEMPATH\\CodeIgniter.php:898","function":"\u00a0\u00a0\u00a0\u00a0\u00a0\u00a0\u00a0\u00a0App\\Controllers\\Laporan->setoranExcel()","index":"\u00a0\u00a05\u00a0\u00a0\u00a0\u00a0"},{"file":"SYSTEMPATH\\CodeIgniter.php:457","function":"\u00a0\u00a0\u00a0\u00a0\u00a0\u00a0\u00a0\u00a0CodeIgniter\\CodeIgniter->runController()","index":"\u00a0\u00a06\u00a0\u00a0\u00a0\u00a0"},{"file":"SYSTEMPATH\\CodeIgniter.php:340","function":"\u00a0\u00a0\u00a0\u00a0\u00a0\u00a0\u00a0\u00a0CodeIgniter\\CodeIgniter->handleRequest()","index":"\u00a0\u00a07\u00a0\u00a0\u00a0\u00a0"},{"file":"FCPATH\\index.php:67","function":"\u00a0\u00a0\u00a0\u00a0\u00a0\u00a0\u00a0\u00a0CodeIgniter\\CodeIgniter->run()","index":"\u00a0\u00a08\u00a0\u00a0\u00a0\u00a0"},{"file":"SYSTEMPATH\\Commands\\Server\\rewrite.php:43","args":["C:\\xampp\\htdocs\\api_koran\\public\\index.php"],"function":"\u00a0\u00a0\u00a0\u00a0\u00a0\u00a0\u00a0\u00a0require_once()","index":"\u00a0\u00a09\u00a0\u00a0\u00a0\u00a0"}],"trace-file":"APPPATH\\Controllers\\Laporan.php:84","qid":"ffe2a34325f3c2aae17f8093057979f6"},{"hover":"","class":"","duration":"0.29 ms","sql":"<strong>SELECT<\/strong> *\n<strong>FROM<\/strong> `koran`","trace":[{"file":"SYSTEMPATH\\Database\\BaseBuilder.php:1585","function":"\u00a0\u00a0\u00a0\u00a0\u00a0\u00a0\u00a0\u00a0CodeIgniter\\Database\\BaseConnection->query()","index":"\u00a0\u00a01\u00a0\u00a0\u00a0\u00a0"},{"file":"SYSTEMPATH\\Model.php:222","function":"\u00a0\u00a0\u00a0\u00a0\u00a0\u00a0\u00a0\u00a0CodeIgniter\\Database\\BaseBuilder->get()","index":"\u00a0\u00a02\u00a0\u00a0\u00a0\u00a0"},{"file":"SYSTEMPATH\\BaseModel.php:584","function":"\u00a0\u00a0\u00a0\u00a0\u00a0\u00a0\u00a0\u00a0CodeIgniter\\Model->doFindAll()","index":"\u00a0\u00a03\u00a0\u00a0\u00a0\u00a0"},{"file":"APPPATH\\Controllers\\Laporan.php:90","function":"\u00a0\u00a0\u00a0\u00a0\u00a0\u00a0\u00a0\u00a0CodeIgniter\\BaseModel->findAll()","index":"\u00a0\u00a04\u00a0\u00a0\u00a0\u00a0"},{"file":"SYSTEMPATH\\CodeIgniter.php:898","function":"\u00a0\u00a0\u00a0\u00a0\u00a0\u00a0\u00a0\u00a0App\\Controllers\\Laporan->setoranExcel()","index":"\u00a0\u00a05\u00a0\u00a0\u00a0\u00a0"},{"file":"SYSTEMPATH\\CodeIgniter.php:457","function":"\u00a0\u00a0\u00a0\u00a0\u00a0\u00a0\u00a0\u00a0CodeIgniter\\CodeIgniter->runController()","index":"\u00a0\u00a06\u00a0\u00a0\u00a0\u00a0"},{"file":"SYSTEMPATH\\CodeIgniter.php:340","function":"\u00a0\u00a0\u00a0\u00a0\u00a0\u00a0\u00a0\u00a0CodeIgniter\\CodeIgniter->handleRequest()","index":"\u00a0\u00a07\u00a0\u00a0\u00a0\u00a0"},{"file":"FCPATH\\index.php:67","function":"\u00a0\u00a0\u00a0\u00a0\u00a0\u00a0\u00a0\u00a0CodeIgniter\\CodeIgniter->run()","index":"\u00a0\u00a08\u00a0\u00a0\u00a0\u00a0"},{"file":"SYSTEMPATH\\Commands\\Server\\rewrite.php:43","args":["C:\\xampp\\htdocs\\api_koran\\public\\index.php"],"function":"\u00a0\u00a0\u00a0\u00a0\u00a0\u00a0\u00a0\u00a0require_once()","index":"\u00a0\u00a09\u00a0\u00a0\u00a0\u00a0"}],"trace-file":"APPPATH\\Controllers\\Laporan.php:90","qid":"ceec6df91220bcf82a830bede875e906"},{"hover":"","class":"","duration":"0.38 ms","sql":"<strong>SELECT<\/strong> *\n<strong>FROM<\/strong> `setoran`\n<strong>WHERE<\/strong> `tanggal` BETWEEN &quot;2022-10-01&quot; and &quot;2022-10-31&quot;&amp;&amp; `nama_koran` <strong>LIKE<\/strong> &quot;Tribun news&quot;","trace":[{"file":"SYSTEMPATH\\Database\\BaseBuilder.php:1585","function":"\u00a0\u00a0\u00a0\u00a0\u00a0\u00a0\u00a0\u00a0CodeIgniter\\Database\\BaseConnection->query()","index":"\u00a0\u00a01\u00a0\u00a0\u00a0\u00a0"},{"file":"SYSTEMPATH\\Model.php:222","function":"\u00a0\u00a0\u00a0\u00a0\u00a0\u00a0\u00a0\u00a0CodeIgniter\\Database\\BaseBuilder->get()","index":"\u00a0\u00a02\u00a0\u00a0\u00a0\u00a0"},{"file":"SYSTEMPATH\\BaseModel.php:584","function":"\u00a0\u00a0\u00a0\u00a0\u00a0\u00a0\u00a0\u00a0CodeIgniter\\Model->doFindAll()","index":"\u00a0\u00a03\u00a0\u00a0\u00a0\u00a0"},{"file":"APPPATH\\Controllers\\Laporan.php:98","function":"\u00a0\u00a0\u00a0\u00a0\u00a0\u00a0\u00a0\u00a0CodeIgniter\\BaseModel->findAll()","index":"\u00a0\u00a04\u00a0\u00a0\u00a0\u00a0"},{"file":"SYSTEMPATH\\CodeIgniter.php:898","function":"\u00a0\u00a0\u00a0\u00a0\u00a0\u00a0\u00a0\u00a0App\\Controllers\\Laporan->setoranExcel()","index":"\u00a0\u00a05\u00a0\u00a0\u00a0\u00a0"},{"file":"SYSTEMPATH\\CodeIgniter.php:457","function":"\u00a0\u00a0\u00a0\u00a0\u00a0\u00a0\u00a0\u00a0CodeIgniter\\CodeIgniter->runController()","index":"\u00a0\u00a06\u00a0\u00a0\u00a0\u00a0"},{"file":"SYSTEMPATH\\CodeIgniter.php:340","function":"\u00a0\u00a0\u00a0\u00a0\u00a0\u00a0\u00a0\u00a0CodeIgniter\\CodeIgniter->handleRequest()","index":"\u00a0\u00a07\u00a0\u00a0\u00a0\u00a0"},{"file":"FCPATH\\index.php:67","function":"\u00a0\u00a0\u00a0\u00a0\u00a0\u00a0\u00a0\u00a0CodeIgniter\\CodeIgniter->run()","index":"\u00a0\u00a08\u00a0\u00a0\u00a0\u00a0"},{"file":"SYSTEMPATH\\Commands\\Server\\rewrite.php:43","args":["C:\\xampp\\htdocs\\api_koran\\public\\index.php"],"function":"\u00a0\u00a0\u00a0\u00a0\u00a0\u00a0\u00a0\u00a0require_once()","index":"\u00a0\u00a09\u00a0\u00a0\u00a0\u00a0"}],"trace-file":"APPPATH\\Controllers\\Laporan.php:98","qid":"8f1ffe23b490fe0df4eee8f60fc8d788"},{"hover":"","class":"","duration":"0.23 ms","sql":"<strong>SELECT<\/strong> *\n<strong>FROM<\/strong> `setoran`\n<strong>WHERE<\/strong> `tanggal` BETWEEN &quot;2022-10-01&quot; and &quot;2022-10-31&quot;&amp;&amp; `nama_koran` <strong>LIKE<\/strong> &quot;Habar Banua&quot;","trace":[{"file":"SYSTEMPATH\\Database\\BaseBuilder.php:1585","function":"\u00a0\u00a0\u00a0\u00a0\u00a0\u00a0\u00a0\u00a0CodeIgniter\\Database\\BaseConnection->query()","index":"\u00a0\u00a01\u00a0\u00a0\u00a0\u00a0"},{"file":"SYSTEMPATH\\Model.php:222","function":"\u00a0\u00a0\u00a0\u00a0\u00a0\u00a0\u00a0\u00a0CodeIgniter\\Database\\BaseBuilder->get()","index":"\u00a0\u00a02\u00a0\u00a0\u00a0\u00a0"},{"file":"SYSTEMPATH\\BaseModel.php:584","function":"\u00a0\u00a0\u00a0\u00a0\u00a0\u00a0\u00a0\u00a0CodeIgniter\\Model->doFindAll()","index":"\u00a0\u00a03\u00a0\u00a0\u00a0\u00a0"},{"file":"APPPATH\\Controllers\\Laporan.php:98","function":"\u00a0\u00a0\u00a0\u00a0\u00a0\u00a0\u00a0\u00a0CodeIgniter\\BaseModel->findAll()","index":"\u00a0\u00a04\u00a0\u00a0\u00a0\u00a0"},{"file":"SYSTEMPATH\\CodeIgniter.php:898","function":"\u00a0\u00a0\u00a0\u00a0\u00a0\u00a0\u00a0\u00a0App\\Controllers\\Laporan->setoranExcel()","index":"\u00a0\u00a05\u00a0\u00a0\u00a0\u00a0"},{"file":"SYSTEMPATH\\CodeIgniter.php:457","function":"\u00a0\u00a0\u00a0\u00a0\u00a0\u00a0\u00a0\u00a0CodeIgniter\\CodeIgniter->runController()","index":"\u00a0\u00a06\u00a0\u00a0\u00a0\u00a0"},{"file":"SYSTEMPATH\\CodeIgniter.php:340","function":"\u00a0\u00a0\u00a0\u00a0\u00a0\u00a0\u00a0\u00a0CodeIgniter\\CodeIgniter->handleRequest()","index":"\u00a0\u00a07\u00a0\u00a0\u00a0\u00a0"},{"file":"FCPATH\\index.php:67","function":"\u00a0\u00a0\u00a0\u00a0\u00a0\u00a0\u00a0\u00a0CodeIgniter\\CodeIgniter->run()","index":"\u00a0\u00a08\u00a0\u00a0\u00a0\u00a0"},{"file":"SYSTEMPATH\\Commands\\Server\\rewrite.php:43","args":["C:\\xampp\\htdocs\\api_koran\\public\\index.php"],"function":"\u00a0\u00a0\u00a0\u00a0\u00a0\u00a0\u00a0\u00a0require_once()","index":"\u00a0\u00a09\u00a0\u00a0\u00a0\u00a0"}],"trace-file":"APPPATH\\Controllers\\Laporan.php:98","qid":"94e7cb3795cfc575190e97aa3ff93961"},{"hover":"","class":"","duration":"0.24 ms","sql":"<strong>SELECT<\/strong> *\n<strong>FROM<\/strong> `setoran`\n<strong>WHERE<\/strong> `tanggal` BETWEEN &quot;2022-10-01&quot; and &quot;2022-10-31&quot;&amp;&amp; `nama_koran` <strong>LIKE<\/strong> &quot;Koran Kalsel&quot;","trace":[{"file":"SYSTEMPATH\\Database\\BaseBuilder.php:1585","function":"\u00a0\u00a0\u00a0\u00a0\u00a0\u00a0\u00a0\u00a0CodeIgniter\\Database\\BaseConnection->query()","index":"\u00a0\u00a01\u00a0\u00a0\u00a0\u00a0"},{"file":"SYSTEMPATH\\Model.php:222","function":"\u00a0\u00a0\u00a0\u00a0\u00a0\u00a0\u00a0\u00a0CodeIgniter\\Database\\BaseBuilder->get()","index":"\u00a0\u00a02\u00a0\u00a0\u00a0\u00a0"},{"file":"SYSTEMPATH\\BaseModel.php:584","function":"\u00a0\u00a0\u00a0\u00a0\u00a0\u00a0\u00a0\u00a0CodeIgniter\\Model->doFindAll()","index":"\u00a0\u00a03\u00a0\u00a0\u00a0\u00a0"},{"file":"APPPATH\\Controllers\\Laporan.php:98","function":"\u00a0\u00a0\u00a0\u00a0\u00a0\u00a0\u00a0\u00a0CodeIgniter\\BaseModel->findAll()","index":"\u00a0\u00a04\u00a0\u00a0\u00a0\u00a0"},{"file":"SYSTEMPATH\\CodeIgniter.php:898","function":"\u00a0\u00a0\u00a0\u00a0\u00a0\u00a0\u00a0\u00a0App\\Controllers\\Laporan->setoranExcel()","index":"\u00a0\u00a05\u00a0\u00a0\u00a0\u00a0"},{"file":"SYSTEMPATH\\CodeIgniter.php:457","function":"\u00a0\u00a0\u00a0\u00a0\u00a0\u00a0\u00a0\u00a0CodeIgniter\\CodeIgniter->runController()","index":"\u00a0\u00a06\u00a0\u00a0\u00a0\u00a0"},{"file":"SYSTEMPATH\\CodeIgniter.php:340","function":"\u00a0\u00a0\u00a0\u00a0\u00a0\u00a0\u00a0\u00a0CodeIgniter\\CodeIgniter->handleRequest()","index":"\u00a0\u00a07\u00a0\u00a0\u00a0\u00a0"},{"file":"FCPATH\\index.php:67","function":"\u00a0\u00a0\u00a0\u00a0\u00a0\u00a0\u00a0\u00a0CodeIgniter\\CodeIgniter->run()","index":"\u00a0\u00a08\u00a0\u00a0\u00a0\u00a0"},{"file":"SYSTEMPATH\\Commands\\Server\\rewrite.php:43","args":["C:\\xampp\\htdocs\\api_koran\\public\\index.php"],"function":"\u00a0\u00a0\u00a0\u00a0\u00a0\u00a0\u00a0\u00a0require_once()","index":"\u00a0\u00a09\u00a0\u00a0\u00a0\u00a0"}],"trace-file":"APPPATH\\Controllers\\Laporan.php:98","qid":"05d8e61ef35e3ce7b9e2c38e9a26cb11"},{"hover":"","class":"","duration":"0.27 ms","sql":"<strong>SELECT<\/strong> *\n<strong>FROM<\/strong> `setoran`\n<strong>WHERE<\/strong> `tanggal` BETWEEN &quot;2022-10-01&quot; and &quot;2022-10-31&quot;&amp;&amp; `nama_koran` <strong>LIKE<\/strong> &quot;Banjarmasin Post&quot;","trace":[{"file":"SYSTEMPATH\\Database\\BaseBuilder.php:1585","function":"\u00a0\u00a0\u00a0\u00a0\u00a0\u00a0\u00a0\u00a0CodeIgniter\\Database\\BaseConnection->query()","index":"\u00a0\u00a01\u00a0\u00a0\u00a0\u00a0"},{"file":"SYSTEMPATH\\Model.php:222","function":"\u00a0\u00a0\u00a0\u00a0\u00a0\u00a0\u00a0\u00a0CodeIgniter\\Database\\BaseBuilder->get()","index":"\u00a0\u00a02\u00a0\u00a0\u00a0\u00a0"},{"file":"SYSTEMPATH\\BaseModel.php:584","function":"\u00a0\u00a0\u00a0\u00a0\u00a0\u00a0\u00a0\u00a0CodeIgniter\\Model->doFindAll()","index":"\u00a0\u00a03\u00a0\u00a0\u00a0\u00a0"},{"file":"APPPATH\\Controllers\\Laporan.php:98","function":"\u00a0\u00a0\u00a0\u00a0\u00a0\u00a0\u00a0\u00a0CodeIgniter\\BaseModel->findAll()","index":"\u00a0\u00a04\u00a0\u00a0\u00a0\u00a0"},{"file":"SYSTEMPATH\\CodeIgniter.php:898","function":"\u00a0\u00a0\u00a0\u00a0\u00a0\u00a0\u00a0\u00a0App\\Controllers\\Laporan->setoranExcel()","index":"\u00a0\u00a05\u00a0\u00a0\u00a0\u00a0"},{"file":"SYSTEMPATH\\CodeIgniter.php:457","function":"\u00a0\u00a0\u00a0\u00a0\u00a0\u00a0\u00a0\u00a0CodeIgniter\\CodeIgniter->runController()","index":"\u00a0\u00a06\u00a0\u00a0\u00a0\u00a0"},{"file":"SYSTEMPATH\\CodeIgniter.php:340","function":"\u00a0\u00a0\u00a0\u00a0\u00a0\u00a0\u00a0\u00a0CodeIgniter\\CodeIgniter->handleRequest()","index":"\u00a0\u00a07\u00a0\u00a0\u00a0\u00a0"},{"file":"FCPATH\\index.php:67","function":"\u00a0\u00a0\u00a0\u00a0\u00a0\u00a0\u00a0\u00a0CodeIgniter\\CodeIgniter->run()","index":"\u00a0\u00a08\u00a0\u00a0\u00a0\u00a0"},{"file":"SYSTEMPATH\\Commands\\Server\\rewrite.php:43","args":["C:\\xampp\\htdocs\\api_koran\\public\\index.php"],"function":"\u00a0\u00a0\u00a0\u00a0\u00a0\u00a0\u00a0\u00a0require_once()","index":"\u00a0\u00a09\u00a0\u00a0\u00a0\u00a0"}],"trace-file":"APPPATH\\Controllers\\Laporan.php:98","qid":"5bfabfdae110c9a609d227d35e910c71"},{"hover":"","class":"","duration":"0.23 ms","sql":"<strong>SELECT<\/strong> *\n<strong>FROM<\/strong> `setoran`\n<strong>WHERE<\/strong> `tanggal` BETWEEN &quot;2022-10-01&quot; and &quot;2022-10-31&quot;&amp;&amp; `nama_koran` <strong>LIKE<\/strong> &quot;Kandangan post&quot;","trace":[{"file":"SYSTEMPATH\\Database\\BaseBuilder.php:1585","function":"\u00a0\u00a0\u00a0\u00a0\u00a0\u00a0\u00a0\u00a0CodeIgniter\\Database\\BaseConnection->query()","index":"\u00a0\u00a01\u00a0\u00a0\u00a0\u00a0"},{"file":"SYSTEMPATH\\Model.php:222","function":"\u00a0\u00a0\u00a0\u00a0\u00a0\u00a0\u00a0\u00a0CodeIgniter\\Database\\BaseBuilder->get()","index":"\u00a0\u00a02\u00a0\u00a0\u00a0\u00a0"},{"file":"SYSTEMPATH\\BaseModel.php:584","function":"\u00a0\u00a0\u00a0\u00a0\u00a0\u00a0\u00a0\u00a0CodeIgniter\\Model->doFindAll()","index":"\u00a0\u00a03\u00a0\u00a0\u00a0\u00a0"},{"file":"APPPATH\\Controllers\\Laporan.php:98","function":"\u00a0\u00a0\u00a0\u00a0\u00a0\u00a0\u00a0\u00a0CodeIgniter\\BaseModel->findAll()","index":"\u00a0\u00a04\u00a0\u00a0\u00a0\u00a0"},{"file":"SYSTEMPATH\\CodeIgniter.php:898","function":"\u00a0\u00a0\u00a0\u00a0\u00a0\u00a0\u00a0\u00a0App\\Controllers\\Laporan->setoranExcel()","index":"\u00a0\u00a05\u00a0\u00a0\u00a0\u00a0"},{"file":"SYSTEMPATH\\CodeIgniter.php:457","function":"\u00a0\u00a0\u00a0\u00a0\u00a0\u00a0\u00a0\u00a0CodeIgniter\\CodeIgniter->runController()","index":"\u00a0\u00a06\u00a0\u00a0\u00a0\u00a0"},{"file":"SYSTEMPATH\\CodeIgniter.php:340","function":"\u00a0\u00a0\u00a0\u00a0\u00a0\u00a0\u00a0\u00a0CodeIgniter\\CodeIgniter->handleRequest()","index":"\u00a0\u00a07\u00a0\u00a0\u00a0\u00a0"},{"file":"FCPATH\\index.php:67","function":"\u00a0\u00a0\u00a0\u00a0\u00a0\u00a0\u00a0\u00a0CodeIgniter\\CodeIgniter->run()","index":"\u00a0\u00a08\u00a0\u00a0\u00a0\u00a0"},{"file":"SYSTEMPATH\\Commands\\Server\\rewrite.php:43","args":["C:\\xampp\\htdocs\\api_koran\\public\\index.php"],"function":"\u00a0\u00a0\u00a0\u00a0\u00a0\u00a0\u00a0\u00a0require_once()","index":"\u00a0\u00a09\u00a0\u00a0\u00a0\u00a0"}],"trace-file":"APPPATH\\Controllers\\Laporan.php:98","qid":"65955c809ac88a1020b2ac6ae3fb78f4"}]},"badgeValue":7,"isEmpty":false,"hasTabContent":true,"hasLabel":false,"icon":"data:image\/png;base64,iVBORw0KGgoAAAANSUhEUgAAABgAAAAYCAYAAADgdz34AAAAAXNSR0IArs4c6QAAAARnQU1BAACxjwv8YQUAAAAJcEhZcwAADsMAAA7DAcdvqGQAAADMSURBVEhLY6A3YExLSwsA4nIycQDIDIhRWEBqamo\/UNF\/SjDQjF6ocZgAKPkRiFeEhoYyQ4WIBiA9QAuWAPEHqBAmgLqgHcolGQD1V4DMgHIxwbCxYD+QBqcKINseKo6eWrBioPrtQBq\/BcgY5ht0cUIYbBg2AJKkRxCNWkDQgtFUNJwtABr+F6igE8olGQD114HMgHIxAVDyAhA\/AlpSA8RYUwoeXAPVex5qHCbIyMgwBCkAuQJIY00huDBUz\/mUlBQDqHGjgBjAwAAACexpph6oHSQAAAAASUVORK5CYII=","hasTimelineData":true,"timelineData":[{"name":"Connecting to Database: \"default\"","component":"Database","start":1667480932.834473,"duration":"0.001728"},{"name":"Query","component":"Database","start":1667480932.837377,"duration":"0.000545","query":"<strong>SELECT<\/strong> *\n<strong>FROM<\/strong> `setoran`\n<strong>WHERE<\/strong> `tanggal` BETWEEN &quot;2022-10-01&quot; and &quot;2022-10-31&quot;"},{"name":"Query","component":"Database","start":1667480932.839778,"duration":"0.000287","query":"<strong>SELECT<\/strong> *\n<strong>FROM<\/strong> `koran`"},{"name":"Query","component":"Database","start":1667480932.84023,"duration":"0.000376","query":"<strong>SELECT<\/strong> *\n<strong>FROM<\/strong> `setoran`\n<strong>WHERE<\/strong> `tanggal` BETWEEN &quot;2022-10-01&quot; and &quot;2022-10-31&quot;&amp;&amp; `nama_koran` <strong>LIKE<\/strong> &quot;Tribun news&quot;"},{"name":"Query","component":"Database","start":1667480932.84075,"duration":"0.000230","query":"<strong>SELECT<\/strong> *\n<strong>FROM<\/strong> `setoran`\n<strong>WHERE<\/strong> `tanggal` BETWEEN &quot;2022-10-01&quot; and &quot;2022-10-31&quot;&amp;&amp; `nama_koran` <strong>LIKE<\/strong> &quot;Habar Banua&quot;"},{"name":"Query","component":"Database","start":1667480932.841119,"duration":"0.000241","query":"<strong>SELECT<\/strong> *\n<strong>FROM<\/strong> `setoran`\n<strong>WHERE<\/strong> `tanggal` BETWEEN &quot;2022-10-01&quot; and &quot;2022-10-31&quot;&amp;&amp; `nama_koran` <strong>LIKE<\/strong> &quot;Koran Kalsel&quot;"},{"name":"Query","component":"Database","start":1667480932.841524,"duration":"0.000272","query":"<strong>SELECT<\/strong> *\n<strong>FROM<\/strong> `setoran`\n<strong>WHERE<\/strong> `tanggal` BETWEEN &quot;2022-10-01&quot; and &quot;2022-10-31&quot;&amp;&amp; `nama_koran` <strong>LIKE<\/strong> &quot;Banjarmasin Post&quot;"},{"name":"Query","component":"Database","start":1667480932.841927,"duration":"0.000229","query":"<strong>SELECT<\/strong> *\n<strong>FROM<\/strong> `setoran`\n<strong>WHERE<\/strong> `tanggal` BETWEEN &quot;2022-10-01&quot; and &quot;2022-10-31&quot;&amp;&amp; `nama_koran` <strong>LIKE<\/strong> &quot;Kandangan post&quot;"}]},{"title":"Logs","titleSafe":"logs","titleDetails":"","display":{"logs":[]},"badgeValue":null,"isEmpty":true,"hasTabContent":true,"hasLabel":false,"icon":"data:image\/png;base64,iVBORw0KGgoAAAANSUhEUgAAABgAAAAYCAYAAADgdz34AAAAAXNSR0IArs4c6QAAAARnQU1BAACxjwv8YQUAAAAJcEhZcwAADsMAAA7DAcdvqGQAAACYSURBVEhLYxgFJIHU1FSjtLS0i0D8AYj7gEKMEBkqAaAFF4D4ERCvAFrwH4gDoFIMKSkpFkB+OTEYqgUTACXfA\/GqjIwMQyD9H2hRHlQKJFcBEiMGQ7VgAqCBvUgK32dmZspCpagGGNPT0\/1BLqeF4bQHQJePpiIwhmrBBEADR1MRfgB0+WgqAmOoFkwANHA0FY0CUgEDAwCQ0PUpNB3kqwAAAABJRU5ErkJggg==","hasTimelineData":false,"timelineData":[]},{"title":"Views","titleSafe":"views","titleDetails":"","display":[],"badgeValue":0,"isEmpty":false,"hasTabContent":false,"hasLabel":true,"icon":"data:image\/png;base64,iVBORw0KGgoAAAANSUhEUgAAABgAAAAYCAYAAADgdz34AAAAAXNSR0IArs4c6QAAAARnQU1BAACxjwv8YQUAAAAJcEhZcwAADsMAAA7DAcdvqGQAAADeSURBVEhL7ZSxDcIwEEWNYA0YgGmgyAaJLTcUaaBzQQEVjMEabBQxAdw53zTHiThEovGTfnE\/9rsoRUxhKLOmaa6Uh7X2+UvguLCzVxN1XW9x4EYHzik033Hp3X0LO+DaQG8MDQcuq6qao4qkHuMgQggLvkPLjqh00ZgFDBacMJYFkuwFlH1mshdkZ5JPJERA9JpI6xNCBESvibQ+IURA9JpI6xNCBESvibQ+IURA9DTsuHTOrVFFxixgB\/eUFlU8uKJ0eDBFOu\/9EvoeKnlJS2\/08Tc8NOwQ8sIfMeYFjqKDjdU2sp4AAAAASUVORK5CYII=","hasTimelineData":true,"timelineData":[]},{"title":"Files","titleSafe":"files","titleDetails":"( 229 )","display":{"coreFiles":[{"name":"AutoloadConfig.php","path":"SYSTEMPATH\\Config\\AutoloadConfig.php"},{"name":"Autoloader.php","path":"SYSTEMPATH\\Autoloader\\Autoloader.php"},{"name":"BaseBuilder.php","path":"SYSTEMPATH\\Database\\BaseBuilder.php"},{"name":"BaseCollector.php","path":"SYSTEMPATH\\Debug\\Toolbar\\Collectors\\BaseCollector.php"},{"name":"BaseConfig.php","path":"SYSTEMPATH\\Config\\BaseConfig.php"},{"name":"BaseConnection.php","path":"SYSTEMPATH\\Database\\BaseConnection.php"},{"name":"BaseHandler.php","path":"SYSTEMPATH\\Cache\\Handlers\\BaseHandler.php"},{"name":"BaseHandler.php","path":"SYSTEMPATH\\Session\\Handlers\\BaseHandler.php"},{"name":"BaseModel.php","path":"SYSTEMPATH\\BaseModel.php"},{"name":"BaseResult.php","path":"SYSTEMPATH\\Database\\BaseResult.php"},{"name":"BaseService.php","path":"SYSTEMPATH\\Config\\BaseService.php"},{"name":"Builder.php","path":"SYSTEMPATH\\Database\\MySQLi\\Builder.php"},{"name":"CacheFactory.php","path":"SYSTEMPATH\\Cache\\CacheFactory.php"},{"name":"CacheInterface.php","path":"SYSTEMPATH\\Cache\\CacheInterface.php"},{"name":"CloneableCookieInterface.php","path":"SYSTEMPATH\\Cookie\\CloneableCookieInterface.php"},{"name":"CodeIgniter.php","path":"SYSTEMPATH\\CodeIgniter.php"},{"name":"Common.php","path":"SYSTEMPATH\\Common.php"},{"name":"Config.php","path":"SYSTEMPATH\\Database\\Config.php"},{"name":"Connection.php","path":"SYSTEMPATH\\Database\\MySQLi\\Connection.php"},{"name":"ConnectionInterface.php","path":"SYSTEMPATH\\Database\\ConnectionInterface.php"},{"name":"ContentSecurityPolicy.php","path":"SYSTEMPATH\\HTTP\\ContentSecurityPolicy.php"},{"name":"Controller.php","path":"SYSTEMPATH\\Controller.php"},{"name":"Cookie.php","path":"SYSTEMPATH\\Cookie\\Cookie.php"},{"name":"CookieInterface.php","path":"SYSTEMPATH\\Cookie\\CookieInterface.php"},{"name":"CookieStore.php","path":"SYSTEMPATH\\Cookie\\CookieStore.php"},{"name":"Database.php","path":"SYSTEMPATH\\Database\\Database.php"},{"name":"Database.php","path":"SYSTEMPATH\\Debug\\Toolbar\\Collectors\\Database.php"},{"name":"DebugToolbar.php","path":"SYSTEMPATH\\Filters\\DebugToolbar.php"},{"name":"DotEnv.php","path":"SYSTEMPATH\\Config\\DotEnv.php"},{"name":"Events.php","path":"SYSTEMPATH\\Debug\\Toolbar\\Collectors\\Events.php"},{"name":"Events.php","path":"SYSTEMPATH\\Events\\Events.php"},{"name":"Exceptions.php","path":"SYSTEMPATH\\Debug\\Exceptions.php"},{"name":"Factories.php","path":"SYSTEMPATH\\Config\\Factories.php"},{"name":"Factory.php","path":"SYSTEMPATH\\Config\\Factory.php"},{"name":"FileHandler.php","path":"SYSTEMPATH\\Cache\\Handlers\\FileHandler.php"},{"name":"FileHandler.php","path":"SYSTEMPATH\\Session\\Handlers\\FileHandler.php"},{"name":"FileLocator.php","path":"SYSTEMPATH\\Autoloader\\FileLocator.php"},{"name":"Files.php","path":"SYSTEMPATH\\Debug\\Toolbar\\Collectors\\Files.php"},{"name":"FilterInterface.php","path":"SYSTEMPATH\\Filters\\FilterInterface.php"},{"name":"Filters.php","path":"SYSTEMPATH\\Filters\\Filters.php"},{"name":"FormatRules.php","path":"SYSTEMPATH\\Validation\\FormatRules.php"},{"name":"Header.php","path":"SYSTEMPATH\\HTTP\\Header.php"},{"name":"IncomingRequest.php","path":"SYSTEMPATH\\HTTP\\IncomingRequest.php"},{"name":"Logger.php","path":"SYSTEMPATH\\Log\\Logger.php"},{"name":"Logs.php","path":"SYSTEMPATH\\Debug\\Toolbar\\Collectors\\Logs.php"},{"name":"Message.php","path":"SYSTEMPATH\\HTTP\\Message.php"},{"name":"MessageInterface.php","path":"SYSTEMPATH\\HTTP\\MessageInterface.php"},{"name":"MessageTrait.php","path":"SYSTEMPATH\\HTTP\\MessageTrait.php"},{"name":"Model.php","path":"SYSTEMPATH\\Model.php"},{"name":"Modules.php","path":"SYSTEMPATH\\Modules\\Modules.php"},{"name":"Query.php","path":"SYSTEMPATH\\Database\\Query.php"},{"name":"QueryInterface.php","path":"SYSTEMPATH\\Database\\QueryInterface.php"},{"name":"RendererInterface.php","path":"SYSTEMPATH\\View\\RendererInterface.php"},{"name":"Request.php","path":"SYSTEMPATH\\HTTP\\Request.php"},{"name":"RequestInterface.php","path":"SYSTEMPATH\\HTTP\\RequestInterface.php"},{"name":"RequestTrait.php","path":"SYSTEMPATH\\HTTP\\RequestTrait.php"},{"name":"Response.php","path":"SYSTEMPATH\\HTTP\\Response.php"},{"name":"ResponseInterface.php","path":"SYSTEMPATH\\HTTP\\ResponseInterface.php"},{"name":"ResponseTrait.php","path":"SYSTEMPATH\\API\\ResponseTrait.php"},{"name":"ResponseTrait.php","path":"SYSTEMPATH\\HTTP\\ResponseTrait.php"},{"name":"Result.php","path":"SYSTEMPATH\\Database\\MySQLi\\Result.php"},{"name":"ResultInterface.php","path":"SYSTEMPATH\\Database\\ResultInterface.php"},{"name":"RouteCollection.php","path":"SYSTEMPATH\\Router\\RouteCollection.php"},{"name":"RouteCollectionInterface.php","path":"SYSTEMPATH\\Router\\RouteCollectionInterface.php"},{"name":"Router.php","path":"SYSTEMPATH\\Router\\Router.php"},{"name":"RouterInterface.php","path":"SYSTEMPATH\\Router\\RouterInterface.php"},{"name":"Routes.php","path":"SYSTEMPATH\\Config\\Routes.php"},{"name":"Routes.php","path":"SYSTEMPATH\\Debug\\Toolbar\\Collectors\\Routes.php"},{"name":"Services.php","path":"SYSTEMPATH\\Config\\Services.php"},{"name":"Session.php","path":"SYSTEMPATH\\Session\\Session.php"},{"name":"SessionInterface.php","path":"SYSTEMPATH\\Session\\SessionInterface.php"},{"name":"Timer.php","path":"SYSTEMPATH\\Debug\\Timer.php"},{"name":"Timers.php","path":"SYSTEMPATH\\Debug\\Toolbar\\Collectors\\Timers.php"},{"name":"Toolbar.php","path":"SYSTEMPATH\\Debug\\Toolbar.php"},{"name":"URI.php","path":"SYSTEMPATH\\HTTP\\URI.php"},{"name":"UserAgent.php","path":"SYSTEMPATH\\HTTP\\UserAgent.php"},{"name":"Validation.php","path":"SYSTEMPATH\\Validation\\Validation.php"},{"name":"ValidationInterface.php","path":"SYSTEMPATH\\Validation\\ValidationInterface.php"},{"name":"View.php","path":"SYSTEMPATH\\Config\\View.php"},{"name":"View.php","path":"SYSTEMPATH\\View\\View.php"},{"name":"ViewDecoratorTrait.php","path":"SYSTEMPATH\\View\\ViewDecoratorTrait.php"},{"name":"Views.php","path":"SYSTEMPATH\\Debug\\Toolbar\\Collectors\\Views.php"},{"name":"array_helper.php","path":"SYSTEMPATH\\Helpers\\array_helper.php"},{"name":"bootstrap.php","path":"SYSTEMPATH\\bootstrap.php"},{"name":"rewrite.php","path":"SYSTEMPATH\\Commands\\Server\\rewrite.php"},{"name":"url_helper.php","path":"SYSTEMPATH\\Helpers\\url_helper.php"}],"userFiles":[{"name":"Alignment.php","path":"VENDORPATH\\phpoffice\\phpspreadsheet\\src\\PhpSpreadsheet\\Style\\Alignment.php"},{"name":"App.php","path":"APPPATH\\Config\\App.php"},{"name":"Archive.php","path":"VENDORPATH\\maennchen\\zipstream-php\\src\\Option\\Archive.php"},{"name":"Auth.php","path":"APPPATH\\Filters\\Auth.php"},{"name":"AutoFilter.php","path":"VENDORPATH\\phpoffice\\phpspreadsheet\\src\\PhpSpreadsheet\\Worksheet\\AutoFilter.php"},{"name":"Autoload.php","path":"APPPATH\\Config\\Autoload.php"},{"name":"BaseController.php","path":"APPPATH\\Controllers\\BaseController.php"},{"name":"BaseWriter.php","path":"VENDORPATH\\phpoffice\\phpspreadsheet\\src\\PhpSpreadsheet\\Writer\\BaseWriter.php"},{"name":"Bigint.php","path":"VENDORPATH\\maennchen\\zipstream-php\\src\\Bigint.php"},{"name":"Border.php","path":"VENDORPATH\\phpoffice\\phpspreadsheet\\src\\PhpSpreadsheet\\Style\\Border.php"},{"name":"Borders.php","path":"VENDORPATH\\phpoffice\\phpspreadsheet\\src\\PhpSpreadsheet\\Style\\Borders.php"},{"name":"BranchPruner.php","path":"VENDORPATH\\phpoffice\\phpspreadsheet\\src\\PhpSpreadsheet\\Calculation\\Engine\\BranchPruner.php"},{"name":"Cache.php","path":"APPPATH\\Config\\Cache.php"},{"name":"CacheInterface.php","path":"VENDORPATH\\psr\\simple-cache\\src\\CacheInterface.php"},{"name":"Calculation.php","path":"VENDORPATH\\phpoffice\\phpspreadsheet\\src\\PhpSpreadsheet\\Calculation\\Calculation.php"},{"name":"Category.php","path":"VENDORPATH\\phpoffice\\phpspreadsheet\\src\\PhpSpreadsheet\\Calculation\\Category.php"},{"name":"Cell.php","path":"VENDORPATH\\phpoffice\\phpspreadsheet\\src\\PhpSpreadsheet\\Cell\\Cell.php"},{"name":"CellIterator.php","path":"VENDORPATH\\phpoffice\\phpspreadsheet\\src\\PhpSpreadsheet\\Worksheet\\CellIterator.php"},{"name":"Cells.php","path":"VENDORPATH\\phpoffice\\phpspreadsheet\\src\\PhpSpreadsheet\\Collection\\Cells.php"},{"name":"CellsFactory.php","path":"VENDORPATH\\phpoffice\\phpspreadsheet\\src\\PhpSpreadsheet\\Collection\\CellsFactory.php"},{"name":"Chart.php","path":"VENDORPATH\\phpoffice\\phpspreadsheet\\src\\PhpSpreadsheet\\Writer\\Xlsx\\Chart.php"},{"name":"ClassLoader.php","path":"VENDORPATH\\composer\\ClassLoader.php"},{"name":"CliRenderer.php","path":"VENDORPATH\\kint-php\\kint\\src\\Renderer\\CliRenderer.php"},{"name":"Color.php","path":"VENDORPATH\\phpoffice\\phpspreadsheet\\src\\PhpSpreadsheet\\Style\\Color.php"},{"name":"ColumnDimension.php","path":"VENDORPATH\\phpoffice\\phpspreadsheet\\src\\PhpSpreadsheet\\Worksheet\\ColumnDimension.php"},{"name":"Comments.php","path":"VENDORPATH\\phpoffice\\phpspreadsheet\\src\\PhpSpreadsheet\\Writer\\Xlsx\\Comments.php"},{"name":"Common.php","path":"APPPATH\\Common.php"},{"name":"Constants.php","path":"APPPATH\\Config\\Constants.php"},{"name":"ContentSecurityPolicy.php","path":"APPPATH\\Config\\ContentSecurityPolicy.php"},{"name":"ContentTypes.php","path":"VENDORPATH\\phpoffice\\phpspreadsheet\\src\\PhpSpreadsheet\\Writer\\Xlsx\\ContentTypes.php"},{"name":"Cookie.php","path":"APPPATH\\Config\\Cookie.php"},{"name":"Coordinate.php","path":"VENDORPATH\\phpoffice\\phpspreadsheet\\src\\PhpSpreadsheet\\Cell\\Coordinate.php"},{"name":"CyclicReferenceStack.php","path":"VENDORPATH\\phpoffice\\phpspreadsheet\\src\\PhpSpreadsheet\\Calculation\\Engine\\CyclicReferenceStack.php"},{"name":"DataSeries.php","path":"VENDORPATH\\phpoffice\\phpspreadsheet\\src\\PhpSpreadsheet\\Chart\\DataSeries.php"},{"name":"DataType.php","path":"VENDORPATH\\phpoffice\\phpspreadsheet\\src\\PhpSpreadsheet\\Cell\\DataType.php"},{"name":"Database.php","path":"APPPATH\\Config\\Database.php"},{"name":"Date.php","path":"VENDORPATH\\phpoffice\\phpspreadsheet\\src\\PhpSpreadsheet\\Shared\\Date.php"},{"name":"DefaultValueBinder.php","path":"VENDORPATH\\phpoffice\\phpspreadsheet\\src\\PhpSpreadsheet\\Cell\\DefaultValueBinder.php"},{"name":"DefinedNames.php","path":"VENDORPATH\\phpoffice\\phpspreadsheet\\src\\PhpSpreadsheet\\Writer\\Xlsx\\DefinedNames.php"},{"name":"Dimension.php","path":"VENDORPATH\\phpoffice\\phpspreadsheet\\src\\PhpSpreadsheet\\Worksheet\\Dimension.php"},{"name":"DocProps.php","path":"VENDORPATH\\phpoffice\\phpspreadsheet\\src\\PhpSpreadsheet\\Writer\\Xlsx\\DocProps.php"},{"name":"Drawing.php","path":"VENDORPATH\\phpoffice\\phpspreadsheet\\src\\PhpSpreadsheet\\Writer\\Xlsx\\Drawing.php"},{"name":"Enum.php","path":"VENDORPATH\\myclabs\\php-enum\\src\\Enum.php"},{"name":"Escaper.php","path":"VENDORPATH\\laminas\\laminas-escaper\\src\\Escaper.php"},{"name":"Events.php","path":"APPPATH\\Config\\Events.php"},{"name":"Exceptions.php","path":"APPPATH\\Config\\Exceptions.php"},{"name":"Feature.php","path":"APPPATH\\Config\\Feature.php"},{"name":"File.php","path":"VENDORPATH\\maennchen\\zipstream-php\\src\\File.php"},{"name":"File.php","path":"VENDORPATH\\maennchen\\zipstream-php\\src\\Option\\File.php"},{"name":"Fill.php","path":"VENDORPATH\\phpoffice\\phpspreadsheet\\src\\PhpSpreadsheet\\Style\\Fill.php"},{"name":"Filters.php","path":"APPPATH\\Config\\Filters.php"},{"name":"Font.php","path":"VENDORPATH\\phpoffice\\phpspreadsheet\\src\\PhpSpreadsheet\\Style\\Font.php"},{"name":"Formatter.php","path":"VENDORPATH\\phpoffice\\phpspreadsheet\\src\\PhpSpreadsheet\\Style\\NumberFormat\\Formatter.php"},{"name":"Functions.php","path":"VENDORPATH\\phpoffice\\phpspreadsheet\\src\\PhpSpreadsheet\\Calculation\\Functions.php"},{"name":"Functions.php","path":"VENDORPATH\\phpunit\\phpunit\\src\\Framework\\Assert\\Functions.php"},{"name":"HTMLPurifier.composer.php","path":"VENDORPATH\\ezyang\\htmlpurifier\\library\\HTMLPurifier.composer.php"},{"name":"HashTable.php","path":"VENDORPATH\\phpoffice\\phpspreadsheet\\src\\PhpSpreadsheet\\HashTable.php"},{"name":"HeaderFooter.php","path":"VENDORPATH\\phpoffice\\phpspreadsheet\\src\\PhpSpreadsheet\\Worksheet\\HeaderFooter.php"},{"name":"IComparable.php","path":"VENDORPATH\\phpoffice\\phpspreadsheet\\src\\PhpSpreadsheet\\IComparable.php"},{"name":"IValueBinder.php","path":"VENDORPATH\\phpoffice\\phpspreadsheet\\src\\PhpSpreadsheet\\Cell\\IValueBinder.php"},{"name":"IWriter.php","path":"VENDORPATH\\phpoffice\\phpspreadsheet\\src\\PhpSpreadsheet\\Writer\\IWriter.php"},{"name":"IntOrFloat.php","path":"VENDORPATH\\phpoffice\\phpspreadsheet\\src\\PhpSpreadsheet\\Shared\\IntOrFloat.php"},{"name":"Iterator.php","path":"VENDORPATH\\phpoffice\\phpspreadsheet\\src\\PhpSpreadsheet\\Worksheet\\Iterator.php"},{"name":"Kint.php","path":"APPPATH\\Config\\Kint.php"},{"name":"Kint.php","path":"VENDORPATH\\kint-php\\kint\\src\\Kint.php"},{"name":"Laporan.php","path":"APPPATH\\Controllers\\Laporan.php"},{"name":"Logger.php","path":"APPPATH\\Config\\Logger.php"},{"name":"Logger.php","path":"VENDORPATH\\phpoffice\\phpspreadsheet\\src\\PhpSpreadsheet\\Calculation\\Engine\\Logger.php"},{"name":"LoggerAwareTrait.php","path":"VENDORPATH\\psr\\log\\Psr\\Log\\LoggerAwareTrait.php"},{"name":"LoggerInterface.php","path":"VENDORPATH\\psr\\log\\Psr\\Log\\LoggerInterface.php"},{"name":"Method.php","path":"VENDORPATH\\maennchen\\zipstream-php\\src\\Option\\Method.php"},{"name":"ModelKoran.php","path":"APPPATH\\Models\\ModelKoran.php"},{"name":"ModelSetoran.php","path":"APPPATH\\Models\\ModelSetoran.php"},{"name":"Modules.php","path":"APPPATH\\Config\\Modules.php"},{"name":"NumberFormat.php","path":"VENDORPATH\\phpoffice\\phpspreadsheet\\src\\PhpSpreadsheet\\Style\\NumberFormat.php"},{"name":"PageMargins.php","path":"VENDORPATH\\phpoffice\\phpspreadsheet\\src\\PhpSpreadsheet\\Worksheet\\PageMargins.php"},{"name":"PageSetup.php","path":"VENDORPATH\\phpoffice\\phpspreadsheet\\src\\PhpSpreadsheet\\Worksheet\\PageSetup.php"},{"name":"Paths.php","path":"APPPATH\\Config\\Paths.php"},{"name":"Properties.php","path":"VENDORPATH\\phpoffice\\phpspreadsheet\\src\\PhpSpreadsheet\\Document\\Properties.php"},{"name":"Protection.php","path":"VENDORPATH\\phpoffice\\phpspreadsheet\\src\\PhpSpreadsheet\\Style\\Protection.php"},{"name":"Protection.php","path":"VENDORPATH\\phpoffice\\phpspreadsheet\\src\\PhpSpreadsheet\\Worksheet\\Protection.php"},{"name":"ReferenceHelper.php","path":"VENDORPATH\\phpoffice\\phpspreadsheet\\src\\PhpSpreadsheet\\ReferenceHelper.php"},{"name":"Rels.php","path":"VENDORPATH\\phpoffice\\phpspreadsheet\\src\\PhpSpreadsheet\\Writer\\Xlsx\\Rels.php"},{"name":"RelsRibbon.php","path":"VENDORPATH\\phpoffice\\phpspreadsheet\\src\\PhpSpreadsheet\\Writer\\Xlsx\\RelsRibbon.php"},{"name":"RelsVBA.php","path":"VENDORPATH\\phpoffice\\phpspreadsheet\\src\\PhpSpreadsheet\\Writer\\Xlsx\\RelsVBA.php"},{"name":"Renderer.php","path":"VENDORPATH\\kint-php\\kint\\src\\Renderer\\Renderer.php"},{"name":"RichRenderer.php","path":"VENDORPATH\\kint-php\\kint\\src\\Renderer\\RichRenderer.php"},{"name":"Routes.php","path":"APPPATH\\Config\\Routes.php"},{"name":"Row.php","path":"VENDORPATH\\phpoffice\\phpspreadsheet\\src\\PhpSpreadsheet\\Worksheet\\Row.php"},{"name":"RowCellIterator.php","path":"VENDORPATH\\phpoffice\\phpspreadsheet\\src\\PhpSpreadsheet\\Worksheet\\RowCellIterator.php"},{"name":"RowDimension.php","path":"VENDORPATH\\phpoffice\\phpspreadsheet\\src\\PhpSpreadsheet\\Worksheet\\RowDimension.php"},{"name":"RowIterator.php","path":"VENDORPATH\\phpoffice\\phpspreadsheet\\src\\PhpSpreadsheet\\Worksheet\\RowIterator.php"},{"name":"Rule.php","path":"VENDORPATH\\phpoffice\\phpspreadsheet\\src\\PhpSpreadsheet\\Worksheet\\AutoFilter\\Column\\Rule.php"},{"name":"Security.php","path":"VENDORPATH\\phpoffice\\phpspreadsheet\\src\\PhpSpreadsheet\\Document\\Security.php"},{"name":"Services.php","path":"APPPATH\\Config\\Services.php"},{"name":"Settings.php","path":"VENDORPATH\\phpoffice\\phpspreadsheet\\src\\PhpSpreadsheet\\Settings.php"},{"name":"SheetView.php","path":"VENDORPATH\\phpoffice\\phpspreadsheet\\src\\PhpSpreadsheet\\Worksheet\\SheetView.php"},{"name":"SimpleCache1.php","path":"VENDORPATH\\phpoffice\\phpspreadsheet\\src\\PhpSpreadsheet\\Collection\\Memory\\SimpleCache1.php"},{"name":"Spreadsheet.php","path":"VENDORPATH\\phpoffice\\phpspreadsheet\\src\\PhpSpreadsheet\\Spreadsheet.php"},{"name":"StringHelper.php","path":"VENDORPATH\\phpoffice\\phpspreadsheet\\src\\PhpSpreadsheet\\Shared\\StringHelper.php"},{"name":"StringTable.php","path":"VENDORPATH\\phpoffice\\phpspreadsheet\\src\\PhpSpreadsheet\\Writer\\Xlsx\\StringTable.php"},{"name":"Stringable.php","path":"VENDORPATH\\myclabs\\php-enum\\stubs\\Stringable.php"},{"name":"Style.php","path":"VENDORPATH\\phpoffice\\phpspreadsheet\\src\\PhpSpreadsheet\\Style\\Style.php"},{"name":"Style.php","path":"VENDORPATH\\phpoffice\\phpspreadsheet\\src\\PhpSpreadsheet\\Writer\\Xlsx\\Style.php"},{"name":"Supervisor.php","path":"VENDORPATH\\phpoffice\\phpspreadsheet\\src\\PhpSpreadsheet\\Style\\Supervisor.php"},{"name":"Table.php","path":"VENDORPATH\\phpoffice\\phpspreadsheet\\src\\PhpSpreadsheet\\Writer\\Xlsx\\Table.php"},{"name":"TextRenderer.php","path":"VENDORPATH\\kint-php\\kint\\src\\Renderer\\TextRenderer.php"},{"name":"Theme.php","path":"VENDORPATH\\phpoffice\\phpspreadsheet\\src\\PhpSpreadsheet\\Writer\\Xlsx\\Theme.php"},{"name":"Toolbar.php","path":"APPPATH\\Config\\Toolbar.php"},{"name":"UserAgents.php","path":"APPPATH\\Config\\UserAgents.php"},{"name":"Utils.php","path":"VENDORPATH\\kint-php\\kint\\src\\Utils.php"},{"name":"Validation.php","path":"APPPATH\\Config\\Validation.php"},{"name":"Validations.php","path":"VENDORPATH\\phpoffice\\phpspreadsheet\\src\\PhpSpreadsheet\\Worksheet\\Validations.php"},{"name":"Version.php","path":"VENDORPATH\\maennchen\\zipstream-php\\src\\Option\\Version.php"},{"name":"View.php","path":"APPPATH\\Config\\View.php"},{"name":"Workbook.php","path":"VENDORPATH\\phpoffice\\phpspreadsheet\\src\\PhpSpreadsheet\\Writer\\Xlsx\\Workbook.php"},{"name":"Worksheet.php","path":"VENDORPATH\\phpoffice\\phpspreadsheet\\src\\PhpSpreadsheet\\Worksheet\\Worksheet.php"},{"name":"Worksheet.php","path":"VENDORPATH\\phpoffice\\phpspreadsheet\\src\\PhpSpreadsheet\\Writer\\Xlsx\\Worksheet.php"},{"name":"WriterPart.php","path":"VENDORPATH\\phpoffice\\phpspreadsheet\\src\\PhpSpreadsheet\\Writer\\Xlsx\\WriterPart.php"},{"name":"XMLWriter.php","path":"VENDORPATH\\phpoffice\\phpspreadsheet\\src\\PhpSpreadsheet\\Shared\\XMLWriter.php"},{"name":"Xlsx.php","path":"VENDORPATH\\phpoffice\\phpspreadsheet\\src\\PhpSpreadsheet\\Writer\\Xlsx.php"},{"name":"ZipStream.php","path":"VENDORPATH\\maennchen\\zipstream-php\\src\\ZipStream.php"},{"name":"autoload.php","path":"VENDORPATH\\autoload.php"},{"name":"autoload_real.php","path":"VENDORPATH\\composer\\autoload_real.php"},{"name":"autoload_static.php","path":"VENDORPATH\\composer\\autoload_static.php"},{"name":"bootstrap.php","path":"VENDORPATH\\phpstan\\phpstan\\bootstrap.php"},{"name":"bootstrap.php","path":"VENDORPATH\\rector\\rector\\bootstrap.php"},{"name":"bootstrap.php","path":"VENDORPATH\\symfony\\polyfill-ctype\\bootstrap.php"},{"name":"bootstrap.php","path":"VENDORPATH\\symfony\\polyfill-intl-grapheme\\bootstrap.php"},{"name":"bootstrap.php","path":"VENDORPATH\\symfony\\polyfill-intl-normalizer\\bootstrap.php"},{"name":"bootstrap.php","path":"VENDORPATH\\symfony\\polyfill-mbstring\\bootstrap.php"},{"name":"bootstrap.php","path":"VENDORPATH\\symfony\\polyfill-php73\\bootstrap.php"},{"name":"bootstrap.php","path":"VENDORPATH\\symfony\\polyfill-php80\\bootstrap.php"},{"name":"bootstrap.php","path":"VENDORPATH\\symfony\\polyfill-php81\\bootstrap.php"},{"name":"bulan_helper.php","path":"APPPATH\\Helpers\\bulan_helper.php"},{"name":"deep_copy.php","path":"VENDORPATH\\myclabs\\deep-copy\\src\\DeepCopy\\deep_copy.php"},{"name":"development.php","path":"APPPATH\\Config\\Boot\\development.php"},{"name":"function.php","path":"VENDORPATH\\symfony\\deprecation-contracts\\function.php"},{"name":"functions.php","path":"VENDORPATH\\symfony\\string\\Resources\\functions.php"},{"name":"index.php","path":"FCPATH\\index.php"},{"name":"init.php","path":"VENDORPATH\\kint-php\\kint\\init.php"},{"name":"init_helpers.php","path":"VENDORPATH\\kint-php\\kint\\init_helpers.php"},{"name":"platform_check.php","path":"VENDORPATH\\composer\\platform_check.php"}]},"badgeValue":229,"isEmpty":false,"hasTabContent":true,"hasLabel":false,"icon":"data:image\/png;base64,iVBORw0KGgoAAAANSUhEUgAAABgAAAAYCAYAAADgdz34AAAAAXNSR0IArs4c6QAAAARnQU1BAACxjwv8YQUAAAAJcEhZcwAADsMAAA7DAcdvqGQAAAGBSURBVEhL7ZQ9S8NQGIVTBQUncfMfCO4uLgoKbuKQOWg+OkXERRE1IAXrIHbVDrqIDuLiJgj+gro7S3dnpfq88b1FMTE3VZx64HBzzvvZWxKnj15QCcPwCD5HUfSWR+JtzgmtsUcQBEva5IIm9SwSu+95CAWbUuy67qBa32ByZEDpIaZYZSZMjjQuPcQUq8yEyYEb8FSerYeQVGbAFzJkX1PyQWLhgCz0BxTCekC1Wp0hsa6yokzhed4oje6Iz6rlJEkyIKfUEFtITVtQdAibn5rMyaYsMS+a5wTv8qeXMhcU16QZbKgl3hbs+L4\/pnpdc87MElZgq10p5DxGdq8I7xrvUWUKvG3NbSK7ubngYzdJwSsF7TiOh9VOgfcEz1UayNe3JUPM1RWC5GXYgTfc75B4NBmXJnAtTfpABX0iPvEd9ezALwkplCFXcr9styiNOKc1RRZpaPM9tcqBwlWzGY1qPL9wjqRBgF5BH6j8HWh2S7MHlX8PrmbK+k\/8PzjOOzx1D3i1pKTTAAAAAElFTkSuQmCC","hasTimelineData":false,"timelineData":[]},{"title":"Routes","titleSafe":"routes","titleDetails":"","display":{"matchedRoute":[{"directory":"","controller":"\\App\\Controllers\\Laporan","method":"setoranexcel","paramCount":0,"truePCount":0,"params":[]}],"routes":[{"method":"GET","route":"\/","handler":"\\App\\Controllers\\Login::index"},{"method":"GET","route":"logout","handler":"\\App\\Controllers\\Login::logout"},{"method":"GET","route":"dashboard","handler":"\\App\\Controllers\\Dashboard::index"},{"method":"GET","route":"setoran","handler":"\\App\\Controllers\\Setoran::index"},{"method":"GET","route":"setoran\/new","handler":"\\App\\Controllers\\Setoran::new"},{"method":"GET","route":"setoran\/(.*)\/edit","handler":"\\App\\Controllers\\Setoran::edit\/$1"},{"method":"GET","route":"setoran\/(.*)","handler":"\\App\\Controllers\\Setoran::show\/$1"},{"method":"GET","route":"koran","handler":"\\App\\Controllers\\Koran::index"},{"method":"GET","route":"koran\/new","handler":"\\App\\Controllers\\Koran::new"},{"method":"GET","route":"koran\/(.*)\/edit","handler":"\\App\\Controllers\\Koran::edit\/$1"},{"method":"GET","route":"koran\/(.*)","handler":"\\App\\Controllers\\Koran::show\/$1"},{"method":"GET","route":"user","handler":"\\App\\Controllers\\User::index"},{"method":"GET","route":"user\/new","handler":"\\App\\Controllers\\User::new"},{"method":"GET","route":"user\/(.*)\/edit","handler":"\\App\\Controllers\\User::edit\/$1"},{"method":"GET","route":"user\/(.*)","handler":"\\App\\Controllers\\User::show\/$1"},{"method":"GET","route":"userweb","handler":"\\App\\Controllers\\userWeb::index"},{"method":"GET","route":"koranweb","handler":"\\App\\Controllers\\KoranWeb::index"},{"method":"GET","route":"setoranweb","handler":"\\App\\Controllers\\SetoranWeb::index"},{"method":"GET","route":"laporan","handler":"\\App\\Controllers\\Laporan::index"},{"method":"GET","route":"laporan\/koranexcel","handler":"\\App\\Controllers\\Laporan::koranexcel"},{"method":"GET","route":"userweb\/create","handler":"\\App\\Controllers\\userWeb::create"},{"method":"GET","route":"userweb\/update\/(.*)","handler":"\\App\\Controllers\\userWeb::update\/$1"},{"method":"GET","route":"koranweb\/create","handler":"\\App\\Controllers\\KoranWeb::create"},{"method":"GET","route":"koranweb\/update\/(.*)","handler":"\\App\\Controllers\\KoranWeb::update\/$1"},{"method":"GET","route":"setoranweb\/create","handler":"\\App\\Controllers\\setoranWeb::create"},{"method":"GET","route":"laporan\/setoranexcel","handler":"\\App\\Controllers\\Laporan::setoranexcel"},{"method":"HEAD","route":"userweb\/create","handler":"\\App\\Controllers\\userWeb::create"},{"method":"HEAD","route":"userweb\/update\/(.*)","handler":"\\App\\Controllers\\userWeb::update\/$1"},{"method":"HEAD","route":"koranweb\/create","handler":"\\App\\Controllers\\KoranWeb::create"},{"method":"HEAD","route":"koranweb\/update\/(.*)","handler":"\\App\\Controllers\\KoranWeb::update\/$1"},{"method":"HEAD","route":"setoranweb\/create","handler":"\\App\\Controllers\\setoranWeb::create"},{"method":"HEAD","route":"laporan\/setoranexcel","handler":"\\App\\Controllers\\Laporan::setoranexcel"},{"method":"POST","route":"auth","handler":"\\App\\Controllers\\Login::auth"},{"method":"POST","route":"dashboard\/ubahPW\/(.*)","handler":"\\App\\Controllers\\Dashboard::ubahPW\/$1"},{"method":"POST","route":"setoran","handler":"\\App\\Controllers\\Setoran::create"},{"method":"POST","route":"koran","handler":"\\App\\Controllers\\Koran::create"},{"method":"POST","route":"user","handler":"\\App\\Controllers\\User::create"},{"method":"POST","route":"userweb\/delete\/(.*)","handler":"\\App\\Controllers\\userWeb::delete\/$1"},{"method":"POST","route":"userweb\/verify\/(.*)","handler":"\\App\\Controllers\\userWeb::verify\/$1"},{"method":"POST","route":"koranweb\/delete\/(.*)","handler":"\\App\\Controllers\\KoranWeb::delete\/$1"},{"method":"POST","route":"setoranweb\/update\/(.*)","handler":"\\App\\Controllers\\setoranWeb::update\/$1"},{"method":"POST","route":"setoranweb\/delete\/(.*)","handler":"\\App\\Controllers\\setoranWeb::delete\/$1"},{"method":"POST","route":"setoranweb\/deleteAll","handler":"\\App\\Controllers\\setoranWeb::deleteAll"},{"method":"POST","route":"userweb\/create","handler":"\\App\\Controllers\\userWeb::create"},{"method":"POST","route":"userweb\/update\/(.*)","handler":"\\App\\Controllers\\userWeb::update\/$1"},{"method":"POST","route":"koranweb\/create","handler":"\\App\\Controllers\\KoranWeb::create"},{"method":"POST","route":"koranweb\/update\/(.*)","handler":"\\App\\Controllers\\KoranWeb::update\/$1"},{"method":"POST","route":"setoranweb\/create","handler":"\\App\\Controllers\\setoranWeb::create"},{"method":"POST","route":"laporan\/setoranexcel","handler":"\\App\\Controllers\\Laporan::setoranexcel"},{"method":"PATCH","route":"setoran\/(.*)","handler":"\\App\\Controllers\\Setoran::update\/$1"},{"method":"PATCH","route":"koran\/(.*)","handler":"\\App\\Controllers\\Koran::update\/$1"},{"method":"PATCH","route":"user\/(.*)","handler":"\\App\\Controllers\\User::update\/$1"},{"method":"PATCH","route":"userweb\/create","handler":"\\App\\Controllers\\userWeb::create"},{"method":"PATCH","route":"userweb\/update\/(.*)","handler":"\\App\\Controllers\\userWeb::update\/$1"},{"method":"PATCH","route":"koranweb\/create","handler":"\\App\\Controllers\\KoranWeb::create"},{"method":"PATCH","route":"koranweb\/update\/(.*)","handler":"\\App\\Controllers\\KoranWeb::update\/$1"},{"method":"PATCH","route":"setoranweb\/create","handler":"\\App\\Controllers\\setoranWeb::create"},{"method":"PATCH","route":"laporan\/setoranexcel","handler":"\\App\\Controllers\\Laporan::setoranexcel"},{"method":"PUT","route":"setoran\/(.*)","handler":"\\App\\Controllers\\Setoran::update\/$1"},{"method":"PUT","route":"koran\/(.*)","handler":"\\App\\Controllers\\Koran::update\/$1"},{"method":"PUT","route":"user\/(.*)","handler":"\\App\\Controllers\\User::update\/$1"},{"method":"PUT","route":"userweb\/create","handler":"\\App\\Controllers\\userWeb::create"},{"method":"PUT","route":"userweb\/update\/(.*)","handler":"\\App\\Controllers\\userWeb::update\/$1"},{"method":"PUT","route":"koranweb\/create","handler":"\\App\\Controllers\\KoranWeb::create"},{"method":"PUT","route":"koranweb\/update\/(.*)","handler":"\\App\\Controllers\\KoranWeb::update\/$1"},{"method":"PUT","route":"setoranweb\/create","handler":"\\App\\Controllers\\setoranWeb::create"},{"method":"PUT","route":"laporan\/setoranexcel","handler":"\\App\\Controllers\\Laporan::setoranexcel"},{"method":"DELETE","route":"setoran\/(.*)","handler":"\\App\\Controllers\\Setoran::delete\/$1"},{"method":"DELETE","route":"koran\/(.*)","handler":"\\App\\Controllers\\Koran::delete\/$1"},{"method":"DELETE","route":"user\/(.*)","handler":"\\App\\Controllers\\User::delete\/$1"},{"method":"DELETE","route":"userweb\/create","handler":"\\App\\Controllers\\userWeb::create"},{"method":"DELETE","route":"userweb\/update\/(.*)","handler":"\\App\\Controllers\\userWeb::update\/$1"},{"method":"DELETE","route":"koranweb\/create","handler":"\\App\\Controllers\\KoranWeb::create"},{"method":"DELETE","route":"koranweb\/update\/(.*)","handler":"\\App\\Controllers\\KoranWeb::update\/$1"},{"method":"DELETE","route":"setoranweb\/create","handler":"\\App\\Controllers\\setoranWeb::create"},{"method":"DELETE","route":"laporan\/setoranexcel","handler":"\\App\\Controllers\\Laporan::setoranexcel"},{"method":"OPTIONS","route":"userweb\/create","handler":"\\App\\Controllers\\userWeb::create"},{"method":"OPTIONS","route":"userweb\/update\/(.*)","handler":"\\App\\Controllers\\userWeb::update\/$1"},{"method":"OPTIONS","route":"koranweb\/create","handler":"\\App\\Controllers\\KoranWeb::create"},{"method":"OPTIONS","route":"koranweb\/update\/(.*)","handler":"\\App\\Controllers\\KoranWeb::update\/$1"},{"method":"OPTIONS","route":"setoranweb\/create","handler":"\\App\\Controllers\\setoranWeb::create"},{"method":"OPTIONS","route":"laporan\/setoranexcel","handler":"\\App\\Controllers\\Laporan::setoranexcel"},{"method":"TRACE","route":"userweb\/create","handler":"\\App\\Controllers\\userWeb::create"},{"method":"TRACE","route":"userweb\/update\/(.*)","handler":"\\App\\Controllers\\userWeb::update\/$1"},{"method":"TRACE","route":"koranweb\/create","handler":"\\App\\Controllers\\KoranWeb::create"},{"method":"TRACE","route":"koranweb\/update\/(.*)","handler":"\\App\\Controllers\\KoranWeb::update\/$1"},{"method":"TRACE","route":"setoranweb\/create","handler":"\\App\\Controllers\\setoranWeb::create"},{"method":"TRACE","route":"laporan\/setoranexcel","handler":"\\App\\Controllers\\Laporan::setoranexcel"},{"method":"CONNECT","route":"userweb\/create","handler":"\\App\\Controllers\\userWeb::create"},{"method":"CONNECT","route":"userweb\/update\/(.*)","handler":"\\App\\Controllers\\userWeb::update\/$1"},{"method":"CONNECT","route":"koranweb\/create","handler":"\\App\\Controllers\\KoranWeb::create"},{"method":"CONNECT","route":"koranweb\/update\/(.*)","handler":"\\App\\Controllers\\KoranWeb::update\/$1"},{"method":"CONNECT","route":"setoranweb\/create","handler":"\\App\\Controllers\\setoranWeb::create"},{"method":"CONNECT","route":"laporan\/setoranexcel","handler":"\\App\\Controllers\\Laporan::setoranexcel"},{"method":"CLI","route":"ci(.*)","handler":"\\CodeIgniter\\CLI\\CommandRunner::index\/$1"},{"method":"CLI","route":"userweb\/create","handler":"\\App\\Controllers\\userWeb::create"},{"method":"CLI","route":"userweb\/update\/(.*)","handler":"\\App\\Controllers\\userWeb::update\/$1"},{"method":"CLI","route":"koranweb\/create","handler":"\\App\\Controllers\\KoranWeb::create"},{"method":"CLI","route":"koranweb\/update\/(.*)","handler":"\\App\\Controllers\\KoranWeb::update\/$1"},{"method":"CLI","route":"setoranweb\/create","handler":"\\App\\Controllers\\setoranWeb::create"},{"method":"CLI","route":"laporan\/setoranexcel","handler":"\\App\\Controllers\\Laporan::setoranexcel"}]},"badgeValue":17,"isEmpty":false,"hasTabContent":true,"hasLabel":false,"icon":"data:image\/png;base64,iVBORw0KGgoAAAANSUhEUgAAABgAAAAYCAYAAADgdz34AAAAAXNSR0IArs4c6QAAAARnQU1BAACxjwv8YQUAAAAJcEhZcwAADsMAAA7DAcdvqGQAAAFDSURBVEhL7ZRNSsNQFIUjVXSiOFEcuQIHDpzpxC0IGYeE\/BEInbWlCHEDLsSiuANdhKDjgm6ggtSJ+l25ldrmmTwIgtgDh\/t37r1J+16cX0dRFMtpmu5pWAkrvYjjOB7AETzStBFW+inxu3KUJMmhludQpoflS1zXban4LYqiO224h6VLTHr8Z+z8EpIHFF9gG78nDVmW7UgTHKjsCyY98QP+pcq+g8Ku2s8G8X3f3\/I8b038WZTp+bO38zxfFd+I6YY6sNUvFlSDk9CRhiAI1jX1I9Cfw7GG1UB8LAuwbU0ZwQnbRDeEN5qqBxZMLtE1ti9LtbREnMIuOXnyIf5rGIb7Wq8HmlZgwYBH7ORTcKH5E4mpjeGt9fBZcHE2GCQ3Vt7oTNPNg+FXLHnSsHkw\/FR+Gg2bB8Ptzrst\/v6C\/wrH+QB+duli6MYJdQAAAABJRU5ErkJggg==","hasTimelineData":false,"timelineData":[]},{"title":"Events","titleSafe":"events","titleDetails":"","display":{"events":{"pre_system":{"event":"pre_system","duration":"14.15","count":1},"dbquery":{"event":"dbquery","duration":"0.18","count":7}}},"badgeValue":8,"isEmpty":false,"hasTabContent":true,"hasLabel":false,"icon":"data:image\/png;base64,iVBORw0KGgoAAAANSUhEUgAAABgAAAAYCAYAAADgdz34AAAAAXNSR0IArs4c6QAAAARnQU1BAACxjwv8YQUAAAAJcEhZcwAADsMAAA7DAcdvqGQAAAEASURBVEhL7ZXNDcIwDIVTsRBH1uDQDdquUA6IM1xgCA6MwJUN2hk6AQzAz0vl0ETUxC5VT3zSU5w81\/mRMGZysixbFEVR0jSKNt8geQU9aRpFmp\/keX6AbjZ5oB74vsaN5lSzA4tLSjpBFxsjeSuRy4d2mDdQTWU7YLbXTNN05mKyovj5KL6B7q3hoy3KwdZxBlT+Ipz+jPHrBqOIynZgcZonoukb\/0ckiTHqNvDXtXEAaygRbaB9FvUTjRUHsIYS0QaSp+Dw6wT4hiTmYHOcYZsdLQ2CbXa4ftuuYR4x9vYZgdb4vsFYUdmABMYeukK9\/SUme3KMFQ77+Yfzh8eYF8+orDuDWU5LAAAAAElFTkSuQmCC","hasTimelineData":false,"timelineData":[]}],"vars":{"varData":{"View Data":[]},"session":{"__ci_last_regenerate":"<pre>1667480795<\/pre>","_ci_previous_url":"http:\/\/192.168.100.5:8080\/laporan","id":"1","nama":"admin","logged_in":"<pre>1<\/pre>"},"post":{"dari":"2022-10-01","sampai":"2022-10-31"},"headers":{"Content-Type":"application\/x-www-form-urlencoded","Host":"192.168.100.5:8080","Connection":"keep-alive","Content-Length":"33","Cache-Control":"max-age=0","Upgrade-Insecure-Requests":"1","User-Agent":"Mozilla\/5.0 (Windows NT 10.0; Win64; x64) AppleWebKit\/537.36 (KHTML, like Gecko) Chrome\/106.0.0.0 Safari\/537.36","Origin":"http:\/\/192.168.100.5:8080","Accept":"text\/html,application\/xhtml+xml,application\/xml;q=0.9,image\/avif,image\/webp,image\/apng,*\/*;q=0.8,application\/signed-exchange;v=b3;q=0.9","Referer":"http:\/\/192.168.100.5:8080\/laporan","Accept-Encoding":"gzip, deflate","Accept-Language":"id-ID,id;q=0.9,en;q=0.8","Cookie":"ci_session=dcpdumr22ukt3ovvaifgr28ui42n27aa"},"cookies":{"ci_session":"dcpdumr22ukt3ovvaifgr28ui42n27aa"},"request":"HTTP\/1.1","response":{"statusCode":200,"reason":"OK","contentType":"text\/html; charset=UTF-8","headers":{"Cache-control":"no-store, max-age=0, no-cache","Content-Type":"text\/html; charset=UTF-8"}}},"config":{"ciVersion":"4.2.3","phpVersion":"7.4.10","phpSAPI":"cli-server","environment":"development","baseURL":"http:\/\/192.168.100.5:8080","timezone":"America\/Chicago","locale":"en","cspEnabled":false}}